{"analyser_analyser-use.md":"BDVd_VH5","analyser_getng-strtd.md":"sSL_P9Oz","api_deploy.md":"Dn55erkH","api_g-started.md":"BRzhhMCp","api_upgrade.md":"C9EcKm04","api_xcmanalyser.md":"YAaaIrtS","api_xcmp.md":"C9WurbZa","api_xcmrouter.md":"EJVj_NRA","contribution.md":"CjhvzuIn","index.md":"Ba_1bql8","license.md":"BQ7Uf1AQ","links.md":"BkRA7SE2","migration_v10-to-v11.md":"CskORDHf","router_getting-strtd.md":"Lix779Zk","router_router-use.md":"D5Jkx2yZ","sdk_assetpallet.md":"Bb69g3TS","sdk_getting-started.md":"CRp1LPHu","sdk_nodepallets.md":"CSExQ4Zh","sdk_xcmpallet.md":"BwmKO9TB","sdk_xcmutils.md":"CYvhaM8-","supported.md":"CiGSpS_D","tools_playground.md":"BRP_zUec","visualizer_getting-start.md":"B0rMwP0y","visualizer_user-guide.md":"C9bdGSsc"}
